pyaes/__init__.py
pyaes/aes.py
pyaes/blockfeeder.py
pyaes/util.py
pyaesfix-1.6.1.dist-info/LICENSE.txt
pyaesfix-1.6.1.dist-info/METADATA
pyaesfix-1.6.1.dist-info/WHEEL
pyaesfix-1.6.1.dist-info/top_level.txt
pyaesfix-1.6.1.dist-info/RECORD
